ezFlashCLI/__init__.py
ezFlashCLI/cli.py
ezFlashCLI/flash_database.json
ezFlashCLI/serialCLI.py
ezFlashCLI/ezFlash/__init__.py
ezFlashCLI/ezFlash/pyjlink.py
ezFlashCLI/ezFlash/smartbond/__init__.py
ezFlashCLI/ezFlash/smartbond/smartbondDevices.py
ezFlashCLI/ezFlash/smartbond/supportedDevices.py
ezFlashCLI/ezFlash/smartbond/binaries/secondary_bootloader_531.bin
ezFlashCLI/third-party/segger/99-jlink.rules
ezFlashCLI/third-party/segger/JLinkARM.dll
ezFlashCLI/third-party/segger/JLinkDevices.xml
ezFlashCLI/third-party/segger/JLink_x64.dll
ezFlashCLI/third-party/segger/libjlinkarm.7.98.9.dylib
ezFlashCLI/third-party/segger/libjlinkarm.so.7.98.9
ezFlashCLI/third-party/segger/libjlinkarm_aarch64.so.7.98.9
ezFlashCLI/third-party/segger/libjlinkarm_arm.so.7.98.9
ezFlashCLI/third-party/segger/libjlinkarm_x86.so.7.98.9
ezFlashCLI/third-party/segger/license.txt
ezFlashCLI/third-party/segger/segger_flash_loader_531.elf
ezFlashCLI/third-party/segger/segger_flash_loader_585.elf
ezFlashCLI/third-party/segger/segger_flash_loader_59x_eflash.elf
ezFlashCLI/third-party/segger/segger_flash_loader_68x.elf
ezFlashCLI/third-party/segger/segger_flash_loader_70x_oflash.elf
ezflashcli-1.0.29.dist-info/licenses/LICENSE.txt
ezflashcli-1.0.29.dist-info/METADATA
ezflashcli-1.0.29.dist-info/WHEEL
ezflashcli-1.0.29.dist-info/entry_points.txt
ezflashcli-1.0.29.dist-info/top_level.txt
ezflashcli-1.0.29.dist-info/RECORD
